mlpro_int_hyperopt/__init__.py
mlpro_int_hyperopt/wrappers/__init__.py
mlpro_int_hyperopt/wrappers/hyperopt.py
mlpro_int_hyperopt-1.0.2.dist-info/licenses/LICENSE
mlpro_int_hyperopt-1.0.2.dist-info/METADATA
mlpro_int_hyperopt-1.0.2.dist-info/WHEEL
mlpro_int_hyperopt-1.0.2.dist-info/top_level.txt
mlpro_int_hyperopt-1.0.2.dist-info/RECORD
