Metadata-Version: 2.4
Name: mlpro_int_hyperopt
Version: 1.0.2
Summary: MLPro: Integration Hyperopt
Home-page: https://mlpro-int-hyperopt.readthedocs.io
Author: MLPro Team
Author-email: mlpro@listen.fh-swf.de
Project-URL: Bug Tracker, https://mlpro-int-hyperopt.readthedocs.io
Classifier: Programming Language :: Python :: 3
Classifier: License :: OSI Approved :: Apache Software License
Classifier: Operating System :: OS Independent
Requires-Python: >=3.11
License-File: LICENSE
Provides-Extra: full
Requires-Dist: mlpro[full]>=2.1.0; extra == "full"
Requires-Dist: hyperopt>=0.2.7; extra == "full"
Requires-Dist: setuptools>=80.3.1; extra == "full"
Dynamic: license-file
